babypy/__init__.py
babypy/babypy.py
babypy-0.1.0.dist-info/METADATA
babypy-0.1.0.dist-info/WHEEL
babypy-0.1.0.dist-info/top_level.txt
babypy-0.1.0.dist-info/RECORD
