Metadata-Version: 2.1
Name: babypy
Version: 0.1.0
Summary: A simplified Python library for beginners
Home-page: https://github.com/jagath-sajjan/babypy
Author: Your Name
Author-email: your.email@example.com
Classifier: Development Status :: 3 - Alpha
Classifier: Intended Audience :: Developers
Classifier: License :: OSI Approved :: MIT License
Classifier: Operating System :: OS Independent
Classifier: Programming Language :: Python :: 3
Classifier: Programming Language :: Python :: 3.7
Classifier: Programming Language :: Python :: 3.8
Classifier: Programming Language :: Python :: 3.9
Requires-Python: >=3.7
Requires-Dist: numpy
Requires-Dist: pandas
Requires-Dist: matplotlib
Requires-Dist: pygame
Requires-Dist: requests
Requires-Dist: beautifulsoup4
Requires-Dist: Pillow
Requires-Dist: nltk
Requires-Dist: Flask
Requires-Dist: cryptography
Requires-Dist: geopy
Requires-Dist: pyttsx3
Requires-Dist: qrcode
Requires-Dist: PyPDF2
Requires-Dist: selenium
Requires-Dist: seaborn
Requires-Dist: scikit-learn
Requires-Dist: opencv-python
Requires-Dist: PyAudio
